submititnow/__init__.py
submititnow/cli.py
submititnow/experiment_lib.py
submititnow/experiment_lib_test.py
submititnow/options.py
submititnow/jt/__init__.py
submititnow/jt/utils.py
submititnow/umiacs/__init__.py
submititnow/umiacs/handlers.py
submititnow-0.9.6.data/scripts/jt
submititnow-0.9.6.data/scripts/py-srun
submititnow-0.9.6.data/scripts/slaunch
submititnow-0.9.6.dist-info/LICENSE
submititnow-0.9.6.dist-info/METADATA
submititnow-0.9.6.dist-info/WHEEL
submititnow-0.9.6.dist-info/top_level.txt
submititnow-0.9.6.dist-info/RECORD
