Metadata-Version: 2.1
Name: submititnow
Version: 0.9.6
Summary: A package to make submitit easier to use
Home-page: https://github.com/maharshi95/submititnow
Author: Maharshi Gor
Author-email: maharshigor@gmail.com
License: MIT
Project-URL: Bug Tracker, https://github.com/maharshi95/submititnow/issues
Platform: UNKNOWN
Requires-Python: >=3.8
Requires-Dist: submitit ==1.4.5
Requires-Dist: pandas >=1.5.0
Requires-Dist: typer[all] >=0.7.0
Requires-Dist: rich-cli >=1.8.0
Requires-Dist: rich >=12.6.0
Requires-Dist: tqdm >=4.0.0
Requires-Dist: scandir >=1.10.0
